flowws_structure_pretraining/ClearMetrics.py
flowws_structure_pretraining/ContextMapper.py
flowws_structure_pretraining/ContextSplitDataset.py
flowws_structure_pretraining/DistanceNeighbors.py
flowws_structure_pretraining/FileLoader.py
flowws_structure_pretraining/Frame2Molecule.py
flowws_structure_pretraining/FrameFilter.py
flowws_structure_pretraining/LimitAccuracyCallback.py
flowws_structure_pretraining/LoadModel.py
flowws_structure_pretraining/NearestNeighbors.py
flowws_structure_pretraining/NormalizeNeighborDistance.py
flowws_structure_pretraining/PyriodicLoader.py
flowws_structure_pretraining/SANNeighbors.py
flowws_structure_pretraining/SplitDataset.py
flowws_structure_pretraining/VoronoiNeighbors.py
flowws_structure_pretraining/__init__.py
flowws_structure_pretraining/internal.py
flowws_structure_pretraining/version.py
flowws_structure_pretraining/analysis/AutoencoderVisualizer.py
flowws_structure_pretraining/analysis/BondDenoisingVisualizer.py
flowws_structure_pretraining/analysis/ClassifierPlotter.py
flowws_structure_pretraining/analysis/EmbeddingDistance.py
flowws_structure_pretraining/analysis/EmbeddingDistanceTrajectory.py
flowws_structure_pretraining/analysis/EmbeddingPlotter.py
flowws_structure_pretraining/analysis/EvaluateEmbedding.py
flowws_structure_pretraining/analysis/ExportAttentionMaps.py
flowws_structure_pretraining/analysis/NoisyBondVisualizer.py
flowws_structure_pretraining/analysis/PCAEmbedding.py
flowws_structure_pretraining/analysis/RegressorPlotter.py
flowws_structure_pretraining/analysis/ShiftIdentificationVisualizer.py
flowws_structure_pretraining/analysis/UMAPEmbedding.py
flowws_structure_pretraining/analysis/ViewAttentionMap.py
flowws_structure_pretraining/analysis/__init__.py
flowws_structure_pretraining/analysis/internal.py
flowws_structure_pretraining/models/GalaBondClassifier.py
flowws_structure_pretraining/models/GalaBondRegressor.py
flowws_structure_pretraining/models/GalaBottleneckAutoencoder.py
flowws_structure_pretraining-0.3.1.dist-info/LICENSE
flowws_structure_pretraining-0.3.1.dist-info/METADATA
flowws_structure_pretraining-0.3.1.dist-info/WHEEL
flowws_structure_pretraining-0.3.1.dist-info/entry_points.txt
flowws_structure_pretraining-0.3.1.dist-info/top_level.txt
flowws_structure_pretraining-0.3.1.dist-info/RECORD
